[
    {
        "key": "datr",
        "value": "F46NaOrTvBWZ0HcY78SoUn2X",
        "domain": "facebook.com",
        "path": "/",
        "hostOnly": false,
        "creation": "2025-08-18T13:11:45.630Z",
        "lastAccessed": "2025-08-18T13:11:45.630Z"
    },
    {
        "key": "sb",
        "value": "F46NaNLhJ5mJPA2elIrmnywa",
        "domain": "facebook.com",
        "path": "/",
        "hostOnly": false,
        "creation": "2025-08-18T13:11:45.630Z",
        "lastAccessed": "2025-08-18T13:11:45.630Z"
    },
    {
        "key": "vpd",
        "value": "v1%3B709x347x3.106943368911743",
        "domain": "facebook.com",
        "path": "/",
        "hostOnly": false,
        "creation": "2025-08-18T13:11:45.630Z",
        "lastAccessed": "2025-08-18T13:11:45.630Z"
    },
    {
        "key": "ps_l",
        "value": "1",
        "domain": "facebook.com",
        "path": "/",
        "hostOnly": false,
        "creation": "2025-08-18T13:11:45.630Z",
        "lastAccessed": "2025-08-18T13:11:45.630Z"
    },
    {
        "key": "ps_n",
        "value": "1",
        "domain": "facebook.com",
        "path": "/",
        "hostOnly": false,
        "creation": "2025-08-18T13:11:45.630Z",
        "lastAccessed": "2025-08-18T13:11:45.630Z"
    },
    {
        "key": "pas",
        "value": "61562904170170%3Ad02etZYXbm%2C61555203410066%3AZT6MJNJ5qX",
        "domain": "facebook.com",
        "path": "/",
        "hostOnly": false,
        "creation": "2025-08-18T13:11:45.630Z",
        "lastAccessed": "2025-08-18T13:11:45.630Z"
    },
    {
        "key": "locale",
        "value": "en_GB",
        "domain": "facebook.com",
        "path": "/",
        "hostOnly": false,
        "creation": "2025-08-18T13:11:45.630Z",
        "lastAccessed": "2025-08-18T13:11:45.630Z"
    },
    {
        "key": "m_pixel_ratio",
        "value": "3.106943368911743",
        "domain": "facebook.com",
        "path": "/",
        "hostOnly": false,
        "creation": "2025-08-18T13:11:45.630Z",
        "lastAccessed": "2025-08-18T13:11:45.630Z"
    },
    {
        "key": "wd",
        "value": "400x912",
        "domain": "facebook.com",
        "path": "/",
        "hostOnly": false,
        "creation": "2025-08-18T13:11:45.630Z",
        "lastAccessed": "2025-08-18T13:11:45.630Z"
    },
    {
        "key": "c_user",
        "value": "61555203410066",
        "domain": "facebook.com",
        "path": "/",
        "hostOnly": false,
        "creation": "2025-08-18T13:11:45.630Z",
        "lastAccessed": "2025-08-18T13:11:45.630Z"
    },
    {
        "key": "xs",
        "value": "12%3A64u2k695AG4VvQ%3A2%3A1755522685%3A-1%3A-1",
        "domain": "facebook.com",
        "path": "/",
        "hostOnly": false,
        "creation": "2025-08-18T13:11:45.630Z",
        "lastAccessed": "2025-08-18T13:11:45.630Z"
    },
    {
        "key": "fr",
        "value": "0Zqx0uhijxIGLEsVH.AWcMX2inDYEFOPhVzFvg8CjzKJqIihXRMEtiMEMHJyLbIG8eyn4.BojY4X..AAA.0.0.BooyaC.AWfuEalWEWR5A0bgIm4IPFJDBn8",
        "domain": "facebook.com",
        "path": "/",
        "hostOnly": false,
        "creation": "2025-08-18T13:11:45.630Z",
        "lastAccessed": "2025-08-18T13:11:45.630Z"
    },
    {
        "key": "fbl_st",
        "value": "101731556%3BT%3A29258711",
        "domain": "facebook.com",
        "path": "/",
        "hostOnly": false,
        "creation": "2025-08-18T13:11:45.630Z",
        "lastAccessed": "2025-08-18T13:11:45.630Z"
    },
    {
        "key": "wl_cbv",
        "value": "v2%3Bclient_version%3A2896%3Btimestamp%3A1755522690",
        "domain": "facebook.com",
        "path": "/",
        "hostOnly": false,
        "creation": "2025-08-18T13:11:45.630Z",
        "lastAccessed": "2025-08-18T13:11:45.630Z"
    }
]
